<?xml version="1.0" encoding="UTF-8" standalone="yes"?>
<agentsStatistics>
    <statistics>
        <agentname>multipartyexample.Appaloosa</agentname>
        <totalUndiscountedUtility>1.752447340317903</totalUndiscountedUtility>
        <totalDiscountedUtility>1.752447340317903</totalDiscountedUtility>
        <numberOfSessions>2</numberOfSessions>
        <totalNashDist>0.12039854628366913</totalNashDist>
        <totalWelfare>3.39393832889904</totalWelfare>
        <totalParetoDistance>0.0</totalParetoDistance>
        <meanDiscounted>0.8762236701589515</meanDiscounted>
        <meanNashDistance>0.06019927314183456</meanNashDistance>
        <meanParetoDistance>0.0</meanParetoDistance>
        <meanUndiscounted>0.8762236701589515</meanUndiscounted>
        <meanWelfare>1.69696916444952</meanWelfare>
    </statistics>
    <statistics>
        <agentname>groupY.GroupY</agentname>
        <totalUndiscountedUtility>4.0758562037628066</totalUndiscountedUtility>
        <totalDiscountedUtility>4.0758562037628066</totalDiscountedUtility>
        <numberOfSessions>5</numberOfSessions>
        <totalNashDist>0.6893633857537608</totalNashDist>
        <totalWelfare>8.427171514258413</totalWelfare>
        <totalParetoDistance>0.0</totalParetoDistance>
        <meanDiscounted>0.8151712407525613</meanDiscounted>
        <meanNashDistance>0.13787267715075216</meanNashDistance>
        <meanParetoDistance>0.0</meanParetoDistance>
        <meanUndiscounted>0.8151712407525613</meanUndiscounted>
        <meanWelfare>1.6854343028516827</meanWelfare>
    </statistics>
    <statistics>
        <agentname>C:\Users\og4428\orhun_workspace\Anac\bin\groupY\GroupY.class</agentname>
        <totalUndiscountedUtility>0.0</totalUndiscountedUtility>
        <totalDiscountedUtility>0.0</totalDiscountedUtility>
        <numberOfSessions>3</numberOfSessions>
        <totalNashDist>3.0</totalNashDist>
        <totalWelfare>0.0</totalWelfare>
        <totalParetoDistance>3.0</totalParetoDistance>
        <meanDiscounted>0.0</meanDiscounted>
        <meanNashDistance>1.0</meanNashDistance>
        <meanParetoDistance>1.0</meanParetoDistance>
        <meanUndiscounted>0.0</meanUndiscounted>
        <meanWelfare>0.0</meanWelfare>
    </statistics>
    <statistics>
        <agentname>C:\Users\og4428\orhun_workspace\Anac\bin\multipartyexample\Appaloosa.class</agentname>
        <totalUndiscountedUtility>0.0</totalUndiscountedUtility>
        <totalDiscountedUtility>0.0</totalDiscountedUtility>
        <numberOfSessions>6</numberOfSessions>
        <totalNashDist>6.0</totalNashDist>
        <totalWelfare>0.0</totalWelfare>
        <totalParetoDistance>6.0</totalParetoDistance>
        <meanDiscounted>0.0</meanDiscounted>
        <meanNashDistance>1.0</meanNashDistance>
        <meanParetoDistance>1.0</meanParetoDistance>
        <meanUndiscounted>0.0</meanUndiscounted>
        <meanWelfare>0.0</meanWelfare>
    </statistics>
    <statistics>
        <agentname>agents.anac.y2017.ponpokoagent.PonPokoAgent</agentname>
        <totalUndiscountedUtility>4.287981977162274</totalUndiscountedUtility>
        <totalDiscountedUtility>4.287981977162274</totalDiscountedUtility>
        <numberOfSessions>8</numberOfSessions>
        <totalNashDist>3.6178677702906543</totalNashDist>
        <totalWelfare>8.411461199328514</totalWelfare>
        <totalParetoDistance>3.0</totalParetoDistance>
        <meanDiscounted>0.5359977471452843</meanDiscounted>
        <meanNashDistance>0.4522334712863318</meanNashDistance>
        <meanParetoDistance>0.375</meanParetoDistance>
        <meanUndiscounted>0.5359977471452843</meanUndiscounted>
        <meanWelfare>1.0514326499160642</meanWelfare>
    </statistics>
</agentsStatistics>
